MANIFEST.in
README
REQUIREMENTS
distribute_setup.py
setup.py
src/django_compass.egg-info/PKG-INFO
src/django_compass.egg-info/SOURCES.txt
src/django_compass.egg-info/dependency_links.txt
src/django_compass.egg-info/requires.txt
src/django_compass.egg-info/top_level.txt
src/djcompass/__init__.py
src/djcompass/commands.py
src/djcompass/models.py