Metadata-Version: 1.0
Name: django-compass
Version: 0.1
Summary: Simple compilation of Compass projects for Django.
Home-page: http://bitbucket.org/zacharyvoase/django-compass
Author: Zachary Voase
Author-email: zacharyvoase@me.com
License: UNKNOWN
Platform: UNKNOWN
